norembg/__init__.py
norembg/_version.py
norembg/bg.py
norembg/cli.py
norembg/session_factory.py
norembg/commands/__init__.py
norembg/commands/b_command.py
norembg/commands/d_command.py
norembg/commands/i_command.py
norembg/commands/p_command.py
norembg/commands/s_command.py
norembg/sessions/__init__.py
norembg/sessions/base.py
norembg/sessions/dis_anime.py
norembg/sessions/dis_general_use.py
norembg/sessions/sam.py
norembg/sessions/silueta.py
norembg/sessions/u2net.py
norembg/sessions/u2net_cloth_seg.py
norembg/sessions/u2net_custom.py
norembg/sessions/u2net_human_seg.py
norembg/sessions/u2netp.py
norembg-0.1.1.dist-info/LICENSE.txt
norembg-0.1.1.dist-info/METADATA
norembg-0.1.1.dist-info/WHEEL
norembg-0.1.1.dist-info/entry_points.txt
norembg-0.1.1.dist-info/top_level.txt
norembg-0.1.1.dist-info/RECORD
